[

    {
        "databaseId" : "1",
        "que_numb" : "1",
        "correcAns" : "Philosophy ",
        "userAns" : "Philosophy "
    },
    {
        "databaseId" : "34",
        "que_numb" : "2",
        "correcAns" : "cubism",
        "userAns" : "abstract"
    },
    {
        "databaseId" : "33",
        "que_numb" : "3",
        "correcAns" : "abstract",
        "userAns" : "abstract"
    },
    {
        "databaseId" : "37",
        "que_numb" : "4",
        "correcAns" : "a room devoted to the handlettered copying of manuscripts",
        "userAns" : "a room devoted to the handlettered copying of manuscripts"
    },
    {
        "databaseId" : "40",
        "que_numb" : "5",
        "correcAns" : "thinking about your thinking",
        "userAns" : "thinking about your thinking"
    },
    {
        "databaseId" : "35",
        "que_numb" : "6",
        "correcAns" : "Images incised in rock",
        "userAns" : "Carvings in Temples"
    },
    {
        "databaseId" : "39",
        "que_numb" : "7",
        "correcAns" : "Movable type Printing Press",
        "userAns" : "Movable machines"
    },
    {
        "databaseId" : "41",
        "que_numb" : "8",
        "correcAns" : "All of the above",
        "userAns" : "All of the above"
    },
    {
        "databaseId" : "36",
        "que_numb" : "9",
        "correcAns" : "humanism",
        "userAns" : "humanism"
    },
    {
        "databaseId" : "38",
        "que_numb" : "10",
        "correcAns" : "the ancient Egyptian writing material called papyrus",
        "userAns" : "Petals"
    }
]